piperna/__init__.py
piperna/__main__-Scott’s iMac.py
piperna/__main__.py
piperna/piperna-Scott’s iMac.py
piperna/piperna.py
piperna/data/environs-Scott’s iMac.json
piperna/data/environs.json
piperna/data/genomes.json
piperna/scripts/summarize.R
piperna-1.82.dist-info/METADATA
piperna-1.82.dist-info/PKG-INFO-Scott’s iMac
piperna-1.82.dist-info/WHEEL
piperna-1.82.dist-info/entry_points.txt
piperna-1.82.dist-info/top_level.txt
piperna-1.82.dist-info/RECORD
