Metadata-Version: 2.1
Name: piperna
Version: 1.82
Summary: A python wrapper for fast and parallel processing of bulk RNA Seq data
Home-page: https://github.com/scfurl/piperna.git
Author: Scott Furlan
Author-email: scottfurlan@gmail.com
License: UNKNOWN
Platform: UNKNOWN
Classifier: Programming Language :: Python :: 3
Classifier: License :: OSI Approved :: MIT License
Classifier: Operating System :: OS Independent
Requires-Python: >=2.5
